apkg/__init__.py
apkg/__version__.py
apkg/apkg.py
apkg/config.py
apkg/commands/__init__.py
apkg/commands/clean.py
apkg/commands/create.py
apkg/commands/environment.py
apkg/commands/freeze.py
apkg/commands/info.py
apkg/commands/init.py
apkg/commands/install.py
apkg/commands/list.py
apkg/commands/nixos.py
apkg/commands/search.py
apkg/commands/uninstall.py
apkg/commands/update.py
apkg/commands/upgrade.py
apkg/commands/write_defaults.py
apkg/commands/templates/__init__.py
apkg/commands/templates/gitignore.template
apkg/commands/templates/library.agda-lib
apkg/commands/templates/library.agda-pkg
apkg/service/__init__.py
apkg/service/database.py
apkg/service/logging.py
apkg/service/readLibFile.py
apkg/service/utils.py
apkg/support/__init__.py
apkg/support/nixos/agda_requirements.txt
apkg/support/nixos/deps.nix
apkg/support/nixos/emacs.nix
apkg/support/nixos/hello-world.agda
apkg/support/nixos/shell.nix
agda_pkg-0.1.51.dist-info/LICENSE
agda_pkg-0.1.51.dist-info/METADATA
agda_pkg-0.1.51.dist-info/WHEEL
agda_pkg-0.1.51.dist-info/entry_points.txt
agda_pkg-0.1.51.dist-info/top_level.txt
agda_pkg-0.1.51.dist-info/RECORD
