Metadata-Version: 2.1
Name: agda-pkg
Version: 0.1.51
Summary: A package manager for Agda
Home-page: https://github.com/agda/agda-pkg
Author: Jonathan Prieto-Cubides and https://github.com/agda/agda-pkg/graphs/contributors
Author-email: jonathan.cubides@uib.no
License: MIT
Keywords: agda,package-manager,agda-pkg,apkg
Platform: any
Classifier: Intended Audience :: Developers
Classifier: License :: OSI Approved :: MIT License
Classifier: Operating System :: OS Independent
Classifier: Programming Language :: Python :: 3.6
Requires-Python: >=3.6.0
Requires-Dist: click
Requires-Dist: gitpython
Requires-Dist: pony
Requires-Dist: whoosh
Requires-Dist: ponywhoosh
Requires-Dist: natsort
Requires-Dist: click-log
Requires-Dist: requests
Requires-Dist: humanize
Requires-Dist: Jinja2
Requires-Dist: distlib
Requires-Dist: PyYAML (>=5.1.1)
